test_poetry_tk/__init__.py
test_poetry_tk/main.py
test_poetry_tk-0.1.0.dist-info/WHEEL
test_poetry_tk-0.1.0.dist-info/METADATA
test_poetry_tk-0.1.0.dist-info/RECORD
