Metadata-Version: 2.1
Name: test-poetry-tk
Version: 0.1.0
Summary: 
Author: Thomas Kuoch
Author-email: kuoch.thomas@gmail.com
Requires-Python: >=3.8,<4.0
Classifier: Programming Language :: Python :: 3
Classifier: Programming Language :: Python :: 3.8
Classifier: Programming Language :: Python :: 3.9
Classifier: Programming Language :: Python :: 3.10
Classifier: Programming Language :: Python :: 3.11
Requires-Dist: pandas (>=1.5.2,<2.0.0)
